tess/__init__.py
tess/_voro.cpython-37m-darwin.so
tess/tests.py
tess-0.3.1.dist-info/LICENSE
tess-0.3.1.dist-info/METADATA
tess-0.3.1.dist-info/WHEEL
tess-0.3.1.dist-info/top_level.txt
tess-0.3.1.dist-info/RECORD
