Metadata-Version: 2.1
Name: tess
Version: 0.3.1
Summary: A module for calculating and analyzing Voronoi tessellations
Home-page: https://tess.readthedocs.org
Author: Wendell Smith
Author-email: wackywendell@gmail.com
License: BSD
Keywords: laguerre voronoi tessellation voro++
Platform: UNKNOWN
Classifier: Development Status :: 3 - Alpha
Classifier: Topic :: Scientific/Engineering :: Mathematics
Classifier: Topic :: Scientific/Engineering :: Physics
Classifier: Intended Audience :: Science/Research
Classifier: Operating System :: POSIX :: Linux
Classifier: Programming Language :: Python :: 3
Classifier: License :: OSI Approved :: BSD License
